{
  "ui": {
    "Back": "返回",
    "Continue": "下一步",
    "Start building": "开始构建",
    "Start building your brand": "开始构建你的品牌",
    "See cover differences": "查看封面差异",
    "See video styles": "查看视频风格",
    "See format diversity": "查看格式多样性",
    "ACTIVATE": "激活",
    "Add name & email to activate": "添加姓名和邮箱以激活",
    "Back To Start": "返回起点",
    "What This Activates": "这将激活的内容",
    "What this changes": "这会改变什么",
    "In the System": "在系统中",
    "For Your Reader": "对你的读者",
    "Brand Defined": "品牌已定义",
    "Studio insight": "工作室洞察",
    "Complete": "完成",
    "Step {n} of {total}": "第 {n} 步 / 共 {total} 步",
    "{pct}%": "{pct}%",
    "Position {n} of 10": "第 {n} / 10 位",
    "Listen to position {n}": "聆听位置 {n}",
    "Active": "已激活",
    "Brand Configuration (YAML)": "品牌配置（YAML）",
    "Brand configuration saved": "品牌配置已保存",
    "Signal scores": "信号分数",
    "Jump to Section": "跳转到章节",
    "Pick a topic...": "选择话题…",
    "How this lands for readers": "这对读者的影响",
    "Narrator preview": "旁白预览",
    "Regulating / calm": "调节／平静",
    "Warm empathetic": "温暖共情",
    "Direct / authority": "直接／权威",
    "Secure process": "安全流程",
    "Email only": "仅限邮件",
    "LINE": "LINE",
    "WhatsApp": "WhatsApp",
    "WeChat": "WeChat",
    "FB Messenger": "FB Messenger",
    "Preferred channel": "首选渠道",
    "Brand direction set": "品牌方向已确定",
    "Reader and market chosen": "读者和市场已选择",
    "Launch details ready": "发布详情已就绪",
    "Pearl Prime Brand Studio": "Pearl Prime 品牌工作室",
    "Overall": "总体",
    "Congratulations": "恭喜",
    "Your brand universe is born.": "你的品牌宇宙诞生了。",
    "Your Brand Choices": "你的品牌选择",
    "System Effect": "系统效果",
    "Reader Benefit": "读者收益",
    "Your Brand in One Sentence": "用一句话描述你的品牌",
    "Visual style": "视觉风格",
    "Manga / visual": "漫画／视觉",
    "Books": "书籍"
  },
  "archetypes": {
    "Stillness Lab": "静息实验室",
    "When the body won't stop screaming": "当身体不停呐喊时",
    "Calm": "平静",
    "Somatic": "躯体",
    "Regulation": "调节",
    "Compass Studio": "指南针工作室",
    "For those who feel lost but aren't broken": "献给那些感到迷茫但未破碎的人",
    "Direction": "方向",
    "Identity": "身份",
    "Purpose": "目标",
    "Soft Lantern": "柔光灯笼",
    "Grief doesn't follow a schedule": "悲伤不遵循时间表",
    "Healing": "疗愈",
    "Grief": "悲伤",
    "Tenderness": "温柔",
    "Clear Mind Lab": "澄心实验室",
    "Cut the noise. Execute what matters.": "切断噪音，执行要事",
    "Focus": "专注",
    "Discipline": "自律",
    "Execution": "执行",
    "Phoenix Rising": "凤凰涅槃",
    "The old you has to die for the real you to live": "旧我必须死去，真我才能重生",
    "Awakening": "觉醒",
    "Meaning": "意义",
    "Depth": "深度"
  },
  "personas": {
    "Burned-Out Professional": "倦怠职场人",
    "Drained, numb, running on fumes": "精疲力竭、麻木、靠残存动力硬撑",
    "Reset, relief, permission to stop": "重启、缓解、允许自己停下",
    "Gen Z Navigator": "Gen Z 探索者",
    "Overwhelmed, comparing, scrolling": "压力过载、不断比较、不停刷屏",
    "Direction, validation, real tools": "方向、认可、真实可用的工具",
    "Gen Alpha Explorer": "Gen Alpha 探索者",
    "Growing up overstimulated, emotionally aware early": "在过度刺激中成长，早期具备情感觉察力",
    "Age-appropriate tools, emotional vocabulary, safe guidance": "适龄工具、情感词汇、安全引导",
    "Grief Carrier": "悲伤承载者",
    "Loss, numbness, can't explain it": "失去、麻木、无法言说",
    "Witness, tenderness, not fixing": "被见证、温柔以待、无需「修复」",
    "Anxious Achiever": "焦虑成就者",
    "Succeeding outside, crumbling inside": "外在成功，内在崩塌",
    "Nervous system support, honesty": "神经系统支持、诚实面对",
    "Spiritual Returner": "灵性回归者",
    "Tried everything, still searching": "试过一切，仍在寻找",
    "Depth, authenticity, no fluff": "深度、真实、拒绝空话",
    "Overwhelmed Parent": "疲惫新手父母",
    "Lost identity, no time, guilt": "身份迷失、时间匮乏、充满愧疚",
    "Quick tools, self-compassion": "快速工具、自我慈悲"
  },
  "moments": {
    "2AM — Can't stop thinking": "凌晨 2 点 — 思绪停不下来",
    "After a breakup or loss": "分手或失去之后",
    "Burned out but can't quit": "倦怠却无法停下",
    "Feeling behind in life": "感觉落后于人生",
    "Panic attack / anxiety spike": "恐慌发作 / 焦虑骤升",
    "Sunday dread before Monday": "周日夜晚的周一焦虑"
  },
  "visuals": {
    "Calm / Minimal": "平静 / 极简",
    "Clean, airy, lots of white space": "干净、通透、大量留白",
    "Serene, spacious, breathable": "宁静、开阔、可呼吸",
    "Dark / Intense": "深沉 / 强烈",
    "Moody, contrast-heavy, dramatic": "情绪感、高对比、戏剧化",
    "Powerful, immersive, cinematic": "有力、沉浸、电影感",
    "Earthy / Organic": "大地 / 有机",
    "Natural textures, warm tones": "自然纹理、温暖色调",
    "Grounded, warm, textured": "踏实、温暖、有质感",
    "Bold / Modern": "大胆 / 现代",
    "Sharp typography, geometric": "锐利排版、几何构成",
    "Energetic, decisive, striking": "活力、果断、醒目",
    "Premium / Geometric": "高级 / 几何",
    "Refined, precise, luxury-positioned": "精致、精准、高端定位",
    "Elevated, geometric, timeless": "升华、几何、永恒",
    "Mysterious / Deep": "神秘 / 深邃",
    "Atmospheric, contemplative, subtly luminous": "氛围感、沉思性、微光流转",
    "Intriguing, expansive, still commercial": "引人、开阔、仍具商业感"
  },
  "emotions": {
    "Finally calm": "终于平静",
    "Safe in my body": "在身体里感到安全",
    "Clear-headed": "头脑清晰",
    "In control": "掌控感",
    "Permission to rest": "允许自己休息",
    "Energized": "充满活力",
    "Connected to purpose": "与目标相连",
    "Released": "释放",
    "Less alone": "不再孤单",
    "Forgiven": "被宽恕",
    "Grounded": "踏实落地",
    "Hopeful": "充满希望",
    "Present": "活在当下",
    "Confident": "自信",
    "Resilient": "有韧性"
  },
  "traditions": {
    "Zen Buddhism": "禅宗佛教",
    "Sufi mysticism": "苏菲神秘主义",
    "Vedanta": "吠檀多",
    "Vajrayana": "金刚乘佛教",
    "Taoism": "道教",
    "Stoicism": "斯多葛主义",
    "Buddhist psychology": "佛教心理学",
    "Somatic therapy": "躯体治疗",
    "Polyvagal theory": "多迷走神经理论",
    "Contemplative Christianity": "默观基督教",
    "Indigenous wisdom": "原住民智慧",
    "Secular mindfulness": "世俗正念",
    "Breathwork science": "呼吸科学",
    "Depth psychology": "深度心理学"
  },
  "angles": {
    "Debunk": "破除迷思",
    "Framework": "框架体系",
    "Reveal": "揭示真相",
    "Leverage": "杠杆借力",
    "Origin Story": "溯源起点"
  },
  "topics": {
    "Anxiety at night": "夜间焦虑",
    "Overthinking": "过度思考",
    "Panic & grounding": "恐慌安抚",
    "Sunday dread": "周日焦虑",
    "Burnout recovery": "倦怠恢复",
    "Nervous system reset": "神经系统重置",
    "Decision fatigue": "决策疲劳",
    "Phone addiction": "手机成瘾",
    "Grief timeline": "悲伤周期",
    "Toxic relationship healing": "毒性关系疗愈",
    "Intergenerational trauma": "代际创伤",
    "Heartbreak recovery": "心碎疗愈",
    "Emotional numbness": "情感麻木",
    "Feeling behind": "落后于人",
    "Quarter-life crisis": "青年危机",
    "Identity rebuild": "身份重建",
    "Purpose after 30": "三十岁后的意义",
    "Habit building": "习惯养成",
    "ADHD & productivity": "ADHD 生产力",
    "Dopamine detox": "多巴胺排毒",
    "Deep work": "深度工作",
    "Meditation for beginners": "冥想入门",
    "Meaning after loss": "失去后的意义",
    "Spiritual without religion": "无宗教灵性",
    "Inner peace in chaos": "混乱中的平静",
    "Mindfulness for skeptics": "怀疑者的正念"
  },
  "steps": {
    "Emotional World": "原型",
    "Primary Reader": "读者",
    "Trigger Moment": "时刻",
    "Voice Tone": "语气",
    "Visual Style": "影响",
    "Emotional Outcomes": "视觉",
    "Topics": "主题",
    "Your Brand": "蓝图",
    "Launch": "启动"
  },
  "radarLabels": {
    "Impact": "影响力",
    "Youth": "年轻受众",
    "Reach": "触达范围",
    "Market": "市场",
    "Depth": "目标",
    "Voice": "声音"
  }
}